tf_raft/__init__.py
tf_raft/datasets/__init__.py
tf_raft/datasets/augmentor.py
tf_raft/datasets/dataset.py
tf_raft/datasets/flow_viz.py
tf_raft/datasets/frame_utils.py
tf_raft/layers/__init__.py
tf_raft/layers/corr.py
tf_raft/layers/extractor.py
tf_raft/layers/update.py
tf_raft/losses/__init__.py
tf_raft/losses/losses.py
tf_raft/model.py
tf_raft/training.py
tf_raft-0.1.4.dist-info/LICENSE
tf_raft-0.1.4.dist-info/WHEEL
tf_raft-0.1.4.dist-info/METADATA
tf_raft-0.1.4.dist-info/RECORD
