Metadata-Version: 2.1
Name: tf-raft
Version: 0.1.4
Summary: RAFT (Recurrent All Pairs Field Transforms for Optical Flow) implementation via tf.keras
Home-page: https://github.com/daigo0927/tf-raft
Author: Daigo Hirooka
Author-email: daigo.hirooka@gmail.com
Requires-Python: >=3.6,<4.0
Classifier: Programming Language :: Python :: 3
Classifier: Programming Language :: Python :: 3.6
Classifier: Programming Language :: Python :: 3.7
Classifier: Programming Language :: Python :: 3.8
Classifier: Programming Language :: Python :: 3.9
Requires-Dist: albumentations (>=0.4.6,<0.5.0)
Requires-Dist: tensorflow (>=2.3.0,<3.0.0)
Requires-Dist: tensorflow-addons (>=0.11.1,<0.12.0)
Project-URL: Repository, https://github.com/daigo0927/tf-raft
